pitchtypes/__init__.py
pitchtypes/basetypes.py
pitchtypes/converters.py
pitchtypes/enharmonic.py
pitchtypes/harmonic.py
pitchtypes/logfreq.py
pitchtypes/spelled.py
pitchtypes/spelled_array.py
pitchtypes-0.4.0.dist-info/LICENSE
pitchtypes-0.4.0.dist-info/METADATA
pitchtypes-0.4.0.dist-info/WHEEL
pitchtypes-0.4.0.dist-info/top_level.txt
pitchtypes-0.4.0.dist-info/RECORD
