Metadata-Version: 2.1
Name: pitchtypes
Version: 0.4.0
Summary: musically meaningful pitch and interval types
Home-page: https://github.com/DCMLab/pitchtypes
Author: Robert Lieck
Author-email: robert.lieck@epfl.ch
Classifier: Programming Language :: Python :: 3
Classifier: License :: OSI Approved :: GNU General Public License v3 (GPLv3)
Classifier: Operating System :: OS Independent
Requires-Python: >=3.6
License-File: LICENSE
Requires-Dist: numpy
